Metadata-Version: 2.2
Name: idstring
Version: 2.1.4
Summary: A Python package to create unique, checksummed serial-number strings.
Author: Vernon Cole
Author-email: vernondcole@gmail.com
Project-URL: repository, https://github.com/vernondcole/idstring
Project-URL: documentation, https://github.com/vernondcole/idstring/wiki
Keywords: serial number,string,checksum,Luhn,increment
Classifier: Development Status :: 5 - Production/Stable
Classifier: Intended Audience :: Developers
Classifier: License :: OSI Approved :: GNU General Public License (GPL)
Classifier: Programming Language :: Python
Classifier: Natural Language :: English
Classifier: Operating System :: OS Independent
Classifier: Topic :: Software Development
Classifier: Topic :: Software Development :: Libraries :: Python Modules
